komparse/__init__.py
komparse/ast.py
komparse/char_stream.py
komparse/grammar.py
komparse/parser.py
komparse/scanner.py
komparse/translators.py
komparse-1.4.3.dist-info/LICENSE
komparse-1.4.3.dist-info/METADATA
komparse-1.4.3.dist-info/WHEEL
komparse-1.4.3.dist-info/top_level.txt
komparse-1.4.3.dist-info/RECORD
