Metadata-Version: 2.1
Name: komparse
Version: 1.4.3
Summary: A parser combinator library
Home-page: UNKNOWN
Author: Thomas Bollmeier
Author-email: entwickler@tbollmeier.de
License: Apache-2.0
Keywords: parser development
Platform: UNKNOWN
Classifier: Development Status :: 5 - Production/Stable
Classifier: Intended Audience :: Developers
Classifier: Topic :: Software Development :: Build Tools
Classifier: License :: OSI Approved :: Apache Software License
Classifier: Programming Language :: Python :: 3
